{
    "title": "Verbs",
    "translations": [
        {
            "arabic": "وصل",
            "romanized": "wiSil",
            "english": "Arrive"
        },
        {
            "arabic": "لغى",
            "romanized": "laghaa",
            "english": "To cancel"
        },
        {
            "arabic": "سمع",
            "romanized": "simi3",
            "english": "To listen"
        },
        {
            "arabic": "سرق",
            "romanized": "saraq",
            "english": "To steal"
        },
        {
            "arabic": "اهتم",
            "romanized": "ihtamm",
            "english": "To care"
        },
        {
            "arabic": "بكي",
            "romanized": "bikii",
            "english": "To cry"
        },
        {
            "arabic": "كان بده",
            "romanized": "kaan biddo",
            "english": "To want"
        },
        {
            "arabic": "حضر ",
            "romanized": "HiDir",
            "english": "To watch"
        },
        {
            "arabic": "فاز",
            "romanized": "faaz",
            "english": "To win"
        },
        {
            "arabic": "ساق",
            "romanized": "saaq",
            "english": "To drive"
        },
        {
            "arabic": "تعلم",
            "romanized": "t3allam",
            "english": "To learn"
        },
        {
            "arabic": "صلح ",
            "romanized": "SallaH",
            "english": "To fix/ repair"
        },
        {
            "arabic": "نسي ",
            "romanized": "nisii",
            "english": "To forget"
        },
        {
            "arabic": "أبيض",
            "romanized": "abyaD",
            "english": "White"
        },
        {
            "arabic": "نط",
            "romanized": "naTT",
            "english": "To jump"
        },
        {
            "arabic": "ترك",
            "romanized": "tarak",
            "english": "To leave"
        },
        {
            "arabic": "غنى",
            "romanized": "ghannaa",
            "english": "To sing"
        },
        {
            "arabic": "بلش",
            "romanized": "ballash",
            "english": "To start"
        },
        {
            "arabic": "سمع",
            "romanized": "simi3",
            "english": "To listen"
        },
        {
            "arabic": "رجع",
            "romanized": "riji3",
            "english": "To return"
        },
        {
            "arabic": "عمل",
            "romanized": "3imil",
            "english": "To do"
        },
        {
            "arabic": "سوى",
            "romanized": "sawwaa",
            "english": "To do/ make"
        },
        {
            "arabic": "حركة",
            "romanized": "Harakeh",
            "english": "Move"
        },
        {
            "arabic": "لعب",
            "romanized": "li3ib",
            "english": "To play"
        },
        {
            "arabic": "جهز",
            "romanized": "jahhaz",
            "english": "To prepare"
        },
        {
            "arabic": "قرأ",
            "romanized": "qara’",
            "english": "To Read"
        },
        {
            "arabic": "شال",
            "romanized": "shaal",
            "english": "To remove sth away"
        },
        {
            "arabic": "صلح ",
            "romanized": "SallaH",
            "english": "To fix/ repair"
        },
        {
            "arabic": "عاد",
            "romanized": "3aad",
            "english": "To repeat"
        },
        {
            "arabic": "حجز",
            "romanized": "Hajaz",
            "english": "To reserve"
        },
        {
            "arabic": "رجع",
            "romanized": "riji3",
            "english": "To return"
        },
        {
            "arabic": "ركض",
            "romanized": "rakaD",
            "english": "To run"
        },
        {
            "arabic": "وفر",
            "romanized": "waffar",
            "english": "To save money"
        },
        {
            "arabic": "حكى",
            "romanized": "Hakaa",
            "english": "Say"
        },
        {
            "arabic": "شاف",
            "romanized": "shaaf",
            "english": "To see"
        },
        {
            "arabic": "بعت",
            "romanized": "ba3at",
            "english": "To send"
        },
        {
            "arabic": "استاهل",
            "romanized": "istaahal",
            "english": "To deserve"
        },
        {
            "arabic": "فرجى",
            "romanized": "farjaa",
            "english": "To show"
        },
        {
            "arabic": "نام",
            "romanized": "naam",
            "english": "To sleep"
        },
        {
            "arabic": "حل",
            "romanized": "Hall",
            "english": "To solve"
        },
        {
            "arabic": "صرف",
            "romanized": "Saraf",
            "english": "To spend money"
        },
        {
            "arabic": "وقف",
            "romanized": "wiqif",
            "english": "To stand"
        },
        {
            "arabic": "بلش",
            "romanized": "ballash",
            "english": "To start"
        },
        {
            "arabic": "ضل",
            "romanized": "Dall",
            "english": "To remain/ stay"
        },
        {
            "arabic": "سرق",
            "romanized": "saraq",
            "english": "To steal"
        },
        {
            "arabic": "وقف",
            "romanized": "waqqaf",
            "english": "To stop"
        },
        {
            "arabic": "نجح",
            "romanized": "najaH",
            "english": "To succeed"
        },
        {
            "arabic": "اقترح",
            "romanized": "iqtaraH",
            "english": "To suggest"
        },
        {
            "arabic": "دعم",
            "romanized": "da3am",
            "english": "To support"
        },
        {
            "arabic": "سباحة",
            "romanized": "sibaaHa",
            "english": "Swimming"
        },
        {
            "arabic": "فتح",
            "romanized": "fataH",
            "english": "To open"
        },
        {
            "arabic": "خلط",
            "romanized": "khalaT",
            "english": "To mix"
        },
        {
            "arabic": "سمى",
            "romanized": "sammaa",
            "english": "To call (name)"
        },
        {
            "arabic": "لاحظ",
            "romanized": "laaHaDH",
            "english": "To notice"
        },
        {
            "arabic": "قال",
            "romanized": "qaal",
            "english": "Say/ tell"
        },
        {
            "arabic": "رمى ",
            "romanized": "ramaa",
            "english": "To throw"
        },
        {
            "arabic": "ربط ",
            "romanized": "rabaT",
            "english": "To tie"
        },
        {
            "arabic": "ترجم",
            "romanized": "tarjam",
            "english": "To translate"
        },
        {
            "arabic": "سافر",
            "romanized": "saafar",
            "english": "To travel"
        },
        {
            "arabic": "رجع",
            "romanized": "riji3",
            "english": "To return"
        },
        {
            "arabic": "فهم",
            "romanized": "fihim",
            "english": "To understand"
        },
        {
            "arabic": "زيارة",
            "romanized": "zyaara",
            "english": "Visit"
        },
        {
            "arabic": "استنى ",
            "romanized": "istannaa",
            "english": "To wait"
        },
        {
            "arabic": "صحي",
            "romanized": "SiHi",
            "english": "To wake up"
        },
        {
            "arabic": "مشى",
            "romanized": "mashaa",
            "english": "To walk"
        },
        {
            "arabic": "كان بده",
            "romanized": "kaan biddo",
            "english": "To want"
        },
        {
            "arabic": "حضر ",
            "romanized": "HiDir",
            "english": "To watch"
        },
        {
            "arabic": "فاز",
            "romanized": "faaz",
            "english": "To win"
        },
        {
            "arabic": "تمنى ",
            "romanized": "tmannaa",
            "english": "To wish/ hope"
        }
    ]
}