{
    "title": "Miscellaneous 2",
    "translations": [
        {
            "arabic": "سوق",
            "romanized": "suuq",
            "english": "Market"
        },
        {
            "arabic": "لئيم",
            "romanized": "la’iim",
            "english": "Mean"
        },
        {
            "arabic": "حاجة",
            "romanized": "Haaja",
            "english": "Need"
        },
        {
            "arabic": "عرض",
            "romanized": "3arD",
            "english": "Offer"
        },
        {
            "arabic": "حد",
            "romanized": "Hadd",
            "english": "Border"
        },
        {
            "arabic": "مشهور",
            "romanized": "mashuur",
            "english": "Popular"
        },
        {
            "arabic": "صلاة",
            "romanized": "Salaa",
            "english": "Prayer"
        },
        {
            "arabic": "بياع",
            "romanized": "bayyaa3",
            "english": "Seller"
        },
        {
            "arabic": "زعيم",
            "romanized": "za3iim",
            "english": "Leader"
        },
        {
            "arabic": "صار",
            "romanized": "Saar",
            "english": "Become"
        },
        {
            "arabic": "عكس",
            "romanized": "3aks",
            "english": "Opposite"
        },
        {
            "arabic": "تسليم",
            "romanized": "tasliim",
            "english": "Delivery"
        }
    ]
}